music_kraken/__init__.py
music_kraken/__main__.py
music_kraken/_version.py
music_kraken/audio/__init__.py
music_kraken/audio/codec.py
music_kraken/audio/metadata.py
music_kraken/cli/__init__.py
music_kraken/cli/main_downloader.py
music_kraken/cli/utils.py
music_kraken/cli/informations/__init__.py
music_kraken/cli/informations/paths.py
music_kraken/cli/options/__init__.py
music_kraken/cli/options/cache.py
music_kraken/cli/options/first_config.py
music_kraken/cli/options/frontend.py
music_kraken/cli/options/settings.py
music_kraken/connection/__init__.py
music_kraken/connection/cache.py
music_kraken/connection/connection.py
music_kraken/connection/rotating.py
music_kraken/download/__init__.py
music_kraken/download/page_attributes.py
music_kraken/download/results.py
music_kraken/objects/__init__.py
music_kraken/objects/artwork.py
music_kraken/objects/collection.py
music_kraken/objects/contact.py
music_kraken/objects/country.py
music_kraken/objects/formatted_text.py
music_kraken/objects/lint_default_factories.py
music_kraken/objects/lyrics.py
music_kraken/objects/metadata.py
music_kraken/objects/option.py
music_kraken/objects/parents.py
music_kraken/objects/song.py
music_kraken/objects/source.py
music_kraken/objects/target.py
music_kraken/pages/__init__.py
music_kraken/pages/abstract.py
music_kraken/pages/bandcamp.py
music_kraken/pages/encyclopaedia_metallum.py
music_kraken/pages/musify.py
music_kraken/pages/youtube.py
music_kraken/pages/youtube_music/__init__.py
music_kraken/pages/youtube_music/_list_render.py
music_kraken/pages/youtube_music/_music_object_render.py
music_kraken/pages/youtube_music/super_youtube.py
music_kraken/pages/youtube_music/youtube_music.py
music_kraken/utils/__init__.py
music_kraken/utils/hacking.py
music_kraken/utils/shared.py
music_kraken/utils/string_processing.py
music_kraken/utils/config/__init__.py
music_kraken/utils/config/config.py
music_kraken/utils/config/utils.py
music_kraken/utils/config/attributes/__init__.py
music_kraken-2.0.0.dist-info/METADATA
music_kraken-2.0.0.dist-info/WHEEL
music_kraken-2.0.0.dist-info/entry_points.txt
music_kraken-2.0.0.dist-info/licenses/LICENSE
music_kraken-2.0.0.dist-info/RECORD
